practice/detect.v
module sequence_detector (input wire clk, reset, data_in, output reg detected);
    reg [1:0] state, next_state;

    always @(posedge clk or posedge reset) begin
        if (reset) state <= 2'b00;
        else state <= next_state;
    end

    always @* begin
        case (state)
            2'b00: if (data_in) next_state = 2'b01; else next_state = 2'b00;
            2'b01: if (data_in) next_state = 2'b10; else next_state = 2'b00;
            2'b10: if (~data_in) next_state = 2'b11; else next_state = 2'b10;
            2'b11: if (data_in) next_state = 2'b10; else next_state = 2'b00;
            default: next_state = 2'b00;
        endcase
    end

    always @* begin
        if (state == 2'b11) detected = 1;
        else detected = 0;
    end
endmodule

module tb_sequence_detector;
    reg clk, reset, data_in;
    wire detected;

    // Instantiate the sequence_detector module
    sequence_detector u1 (.clk(clk), .reset(reset), .data_in(data_in), .detected(detected));

    initial begin
        $dumpfile("out2.vcd");
        $dumpvars(0,tb_sequence_detector);
        // Initialize signals
        clk = 0;
        reset = 1;
        data_in = 0;

        // Apply reset
        #10 reset = 0;
        #10 reset = 1;
        #10 reset = 0;

        // Apply input sequence
        #10 data_in = 1;
        #10 data_in = 1;
        #10 data_in = 0;
        #10 data_in = 1;
        #10 data_in = 1;
        #10 data_in = 0;

        // Finish the simulation
        #10 $finish;
    end

    // Generate clock signal
    always #5 clk = ~clk;
endmodule

practice/out2.vcd
$date
	Thu Nov 23 23:45:42 2023
$end
$version
	Icarus Verilog
$end
$timescale
	1s
$end
$scope module tb_sequence_detector $end
$var wire 1 ! detected $end
$var reg 1 " clk $end
$var reg 1 # data_in $end
$var reg 1 $ reset $end
$scope module u1 $end
$var wire 1 " clk $end
$var wire 1 # data_in $end
$var wire 1 $ reset $end
$var reg 1 ! detected $end
$var reg 2 % next_state [1:0] $end
$var reg 2 & state [1:0] $end
$upscope $end
$upscope $end
$enddefinitions $end
$comment Show the parameter values. $end
$dumpall
$end
#0
$dumpvars
b0 &
b0 %
1$
0#
0"
0!
$end
#5
1"
#10
0"
0$
#15
1"
#20
0"
1$
#25
1"
#30
0"
0$
#35
1"
#40
b1 %
0"
1#
#45
b10 %
b1 &
1"
#50
0"
#55
b10 &
1"
#60
b11 %
0"
0#
#65
1!
b0 %
b11 &
1"
#70
b10 %
0"
1#
#75
0!
b10 &
1"
#80
0"
#85
1"
#90
b11 %
0"
0#
#95
1!
b0 %
b11 &
1"
