practice/compare.v
module compare (
    input [3:0] in1,
    input [3:0] in2,
    output reg g,
    output reg e,
    output reg l
);
    always@(in1 or in2) begin
        if(in1>in2) begin
            g<=1;
            e<=0;
            l<=0;
        end
        else if(in1==in2) begin
            g<=0;
            e<=1;
            l<=0;
        end    
        else begin
            g<=0;
            e<=0;
            l<=1;
        end
    end
endmodule

module tb ();
    reg [3:0] in1;
    reg [3:0] in2;
    wire g,e,l;
    compare test(in1,in2,g,e,l);
    initial begin
        $dumpfile("out3.vcd");
        $dumpvars(0,tb);

        // Apply input values
        #10 in1 = 4'b0000; in2 = 4'b0000; // in1 == in2
        #10 in1 = 4'b0001; in2 = 4'b0000; // in1 > in2
        #10 in1 = 4'b0000; in2 = 4'b0001; // in1 < in2
        #10 in1 = 4'b0010; in2 = 4'b0010; // in1 == in2
        #10 in1 = 4'b0011; in2 = 4'b0010; // in1 > in2
        #10 in1 = 4'b0010; in2 = 4'b0011; // in1 < in2
        #10 in1 = 4'b0100; in2 = 4'b0100; // in1 == in2
        #10 in1 = 4'b0101; in2 = 4'b0100; // in1 > in2
        #10 in1 = 4'b0100; in2 = 4'b0101; // in1 < in2
        #10 in1 = 4'b0110; in2 = 4'b0110; // in1 == in2
        #10 in1 = 4'b0111; in2 = 4'b0110; // in1 > in2
        #10 in1 = 4'b0110; in2 = 4'b0111; // in1 < in2
        #10 in1 = 4'b1000; in2 = 4'b1000; // in1 == in2
        #10 in1 = 4'b1001; in2 = 4'b1000; // in1 > in2
        #10 in1 = 4'b1000; in2 = 4'b1001; // in1 < in2
        #10 in1 = 4'b1010; in2 = 4'b1010; // in1 == in2
        #10 in1 = 4'b1011; in2 = 4'b1010; // in1 > in2
        #10 in1 = 4'b1010; in2 = 4'b1011; // in1 < in2
        #10 in1 = 4'b1100; in2 = 4'b1100; // in1 == in2
        #10 in1 = 4'b1101; in2 = 4'b1100; // in1 > in2
        #10 in1 = 4'b1100; in2 = 4'b1101; // in1 < in2
        #10 in1 = 4'b1110; in2 = 4'b1110; // in1 == in2
        #10 in1 = 4'b1111; in2 = 4'b1110; // in1 > in2
        #10 in1 = 4'b1110; in2 = 4'b1111; // in1 < in2
        #10 in1 = 4'b1111; in2 = 4'b1111; // in1 == in2

        // Finish the simulation
        #10 $finish;
    end
endmodule

practice/out3.vcd
$date
	Thu Nov 23 23:59:53 2023
$end
$version
	Icarus Verilog
$end
$timescale
	1s
$end
$scope module tb $end
$var wire 1 ! l $end
$var wire 1 " g $end
$var wire 1 # e $end
$var reg 4 $ in1 [3:0] $end
$var reg 4 % in2 [3:0] $end
$scope module test $end
$var wire 4 & in1 [3:0] $end
$var wire 4 ' in2 [3:0] $end
$var reg 1 # e $end
$var reg 1 " g $end
$var reg 1 ! l $end
$upscope $end
$upscope $end
$enddefinitions $end
$comment Show the parameter values. $end
$dumpall
$end
#0
$dumpvars
bx '
bx &
bx %
bx $
x#
x"
x!
$end
#10
0!
1#
0"
b0 %
b0 '
b0 $
b0 &
#20
0#
1"
b1 $
b1 &
#30
1!
0"
b1 %
b1 '
b0 $
b0 &
#40
0!
1#
b10 %
b10 '
b10 $
b10 &
#50
0#
1"
b11 $
b11 &
#60
1!
0"
b11 %
b11 '
b10 $
b10 &
#70
0!
1#
b100 %
b100 '
b100 $
b100 &
#80
0#
1"
b101 $
b101 &
#90
1!
0"
b101 %
b101 '
b100 $
b100 &
#100
0!
1#
b110 %
b110 '
b110 $
b110 &
#110
0#
1"
b111 $
b111 &
#120
1!
0"
b111 %
b111 '
b110 $
b110 &
#130
0!
1#
b1000 %
b1000 '
b1000 $
b1000 &
#140
0#
1"
b1001 $
b1001 &
#150
1!
0"
b1001 %
b1001 '
b1000 $
b1000 &
#160
0!
1#
b1010 %
b1010 '
b1010 $
b1010 &
#170
0#
1"
b1011 $
b1011 &
#180
1!
0"
b1011 %
b1011 '
b1010 $
b1010 &
#190
0!
1#
b1100 %
b1100 '
b1100 $
b1100 &
#200
0#
1"
b1101 $
b1101 &
#210
1!
0"
b1101 %
b1101 '
b1100 $
b1100 &
#220
0!
1#
b1110 %
b1110 '
b1110 $
b1110 &
#230
0#
1"
b1111 $
b1111 &
#240
1!
0"
b1111 %
b1111 '
b1110 $
b1110 &
#250
0!
1#
b1111 $
b1111 &
