VT6/bcd_c.v
module up_down_bcd_counter (
    input wire clk,
    input wire reset,
    input wire load,
    input wire up_down,
    input wire [3:0] data_in,
    output reg [3:0] count_out
);

reg [3:0] next_count;

always @(posedge clk or posedge reset) begin
    if (reset) begin
        count_out <= 4'b0000;
    end 
    else if (load) begin
        count_out <= data_in;
    end 
    else begin
        count_out <= next_count;
    end
end

always @* begin
    if (up_down) begin // Up count
        if (count_out == 4'b1001)
            next_count = 4'b0000;
        else
            next_count = count_out + 1;
    end 
    else begin // Down count
        if (count_out == 4'b0000)
            next_count = 4'b1001;
        else
            next_count = count_out - 1;
    end
end

endmodule

VT6/tb_bcd.v
`include "bcd_c.v"

module up_down_bcd_counter_testbench();
    reg clk, reset, load, up_down;
    reg [3:0] data_in;
    wire [3:0] count_out;

    up_down_bcd_counter dut(clk, reset, load, up_down, data_in, count_out);

    initial begin 
        clk = 0;
        forever #5 clk = ~clk;
    end

    initial begin
        $dumpfile("out2.vcd");
        $dumpvars(0, up_down_bcd_counter_testbench);
        reset = 1;
        #15;
        reset = 0;
        #200;
        $finish;
    end

    initial begin
        load = 0;
        up_down = 1; // Up count mode
        data_in = 4'b0000; // Test input
        #10;
        load = 1; // Assert load
        data_in = 4'b1001; // Test input
        #10;
        load = 0; // Deassert load
        #20; // Observe the count incrementing
        up_down = 0; // Down count mode
        #20; // Observe the count decrementing
    end
endmodule

VT6/out2.vcd
$date
	Mon Nov 06 23:11:52 2023
$end
$version
	Icarus Verilog
$end
$timescale
	1s
$end
$scope module up_down_bcd_counter_testbench $end
$var wire 4 ! count_out [3:0] $end
$var reg 1 " clk $end
$var reg 4 # data_in [3:0] $end
$var reg 1 $ load $end
$var reg 1 % reset $end
$var reg 1 & up_down $end
$scope module dut $end
$var wire 1 " clk $end
$var wire 4 ' data_in [3:0] $end
$var wire 1 $ load $end
$var wire 1 % reset $end
$var wire 1 & up_down $end
$var reg 4 ( count_out [3:0] $end
$var reg 4 ) next_count [3:0] $end
$upscope $end
$upscope $end
$enddefinitions $end
$comment Show the parameter values. $end
$dumpall
$end
#0
$dumpvars
b1 )
b0 (
b0 '
1&
1%
0$
b0 #
0"
b0 !
$end
#5
1"
#10
0"
b1001 #
b1001 '
1$
#15
b0 )
b1001 !
b1001 (
1"
0%
#20
0"
0$
#25
b1 )
b0 !
b0 (
1"
#30
0"
#35
b10 )
b1 !
b1 (
1"
#40
b0 )
0"
0&
#45
b1001 )
b0 !
b0 (
1"
#50
0"
#55
b1000 )
b1001 !
b1001 (
1"
#60
0"
#65
b111 )
b1000 !
b1000 (
1"
#70
0"
#75
b110 )
b111 !
b111 (
1"
#80
0"
#85
b101 )
b110 !
b110 (
1"
#90
0"
#95
b100 )
b101 !
b101 (
1"
#100
0"
#105
b11 )
b100 !
b100 (
1"
#110
0"
#115
b10 )
b11 !
b11 (
1"
#120
0"
#125
b1 )
b10 !
b10 (
1"
#130
0"
#135
b0 )
b1 !
b1 (
1"
#140
0"
#145
b1001 )
b0 !
b0 (
1"
#150
0"
#155
b1000 )
b1001 !
b1001 (
1"
#160
0"
#165
b111 )
b1000 !
b1000 (
1"
#170
0"
#175
b110 )
b111 !
b111 (
1"
#180
0"
#185
b101 )
b110 !
b110 (
1"
#190
0"
#195
b100 )
b101 !
b101 (
1"
#200
0"
#205
b11 )
b100 !
b100 (
1"
#210
0"
#215
b10 )
b11 !
b11 (
1"
