VT6/counter.v
module up_down_counter (
    input wire clk,
    input wire reset,
    input wire load,
    input wire up_down,
    input wire [3:0] data_in,
    output reg [3:0] count_out
);

always @(posedge clk or posedge reset) begin
    if (reset) begin
        count_out <= 4'b0000;
    end 
    else if (load) begin
        count_out <= data_in;
    end 
    else if (up_down) begin
        count_out <= count_out + 1;
    end 
    else begin
        count_out <= count_out - 1;
    end
end

endmodule

VT6/tb.v
`include "counter.v"

module up_down_counter_testbench();
    reg clk, reset, load, up_down;
    reg [3:0] data_in;
    wire [3:0] count_out;

    up_down_counter dut(clk, reset, load, up_down, data_in, count_out);

    initial begin 
        clk = 0;
        forever #5 clk = ~clk;
    end

    initial begin
        $dumpfile("out3.vcd");
        $dumpvars(0, up_down_counter_testbench);
        reset = 1;
        #15;
        reset = 0;
        #200;
        $finish;
    end

    initial begin
        load = 0;
        up_down = 1; // Up mode
        data_in = 4'b0000; // Test input
        #10;
        load = 1; // Assert load
        data_in = 4'b1010; // Test input
        #10;
        load = 0; // Deassert load
        #20; // Observe the count incrementing
        up_down = 0; // Down mode
        #20; // Observe the count decrementing
    end
endmodule

VT6/out3.vcd
$date
	Mon Nov 06 23:12:04 2023
$end
$version
	Icarus Verilog
$end
$timescale
	1s
$end
$scope module up_down_counter_testbench $end
$var wire 4 ! count_out [3:0] $end
$var reg 1 " clk $end
$var reg 4 # data_in [3:0] $end
$var reg 1 $ load $end
$var reg 1 % reset $end
$var reg 1 & up_down $end
$scope module dut $end
$var wire 1 " clk $end
$var wire 4 ' data_in [3:0] $end
$var wire 1 $ load $end
$var wire 1 % reset $end
$var wire 1 & up_down $end
$var reg 4 ( count_out [3:0] $end
$upscope $end
$upscope $end
$enddefinitions $end
$comment Show the parameter values. $end
$dumpall
$end
#0
$dumpvars
b0 (
b0 '
1&
1%
0$
b0 #
0"
b0 !
$end
#5
1"
#10
0"
b1010 #
b1010 '
1$
#15
b1010 !
b1010 (
1"
0%
#20
0"
0$
#25
b1011 !
b1011 (
1"
#30
0"
#35
b1100 !
b1100 (
1"
#40
0"
0&
#45
b1011 !
b1011 (
1"
#50
0"
#55
b1010 !
b1010 (
1"
#60
0"
#65
b1001 !
b1001 (
1"
#70
0"
#75
b1000 !
b1000 (
1"
#80
0"
#85
b111 !
b111 (
1"
#90
0"
#95
b110 !
b110 (
1"
#100
0"
#105
b101 !
b101 (
1"
#110
0"
#115
b100 !
b100 (
1"
#120
0"
#125
b11 !
b11 (
1"
#130
0"
#135
b10 !
b10 (
1"
#140
0"
#145
b1 !
b1 (
1"
#150
0"
#155
b0 !
b0 (
1"
#160
0"
#165
b1111 !
b1111 (
1"
#170
0"
#175
b1110 !
b1110 (
1"
#180
0"
#185
b1101 !
b1101 (
1"
#190
0"
#195
b1100 !
b1100 (
1"
#200
0"
#205
b1011 !
b1011 (
1"
#210
0"
#215
b1010 !
b1010 (
1"
