VT6/ring_c.v
module ring_counter (
    input wire clk,
    input wire reset,
    output reg [3:0] count_out
);

always @(posedge clk or posedge reset) begin
    if (reset) begin
        count_out <= 4'b0001;
    end else begin
        count_out <= {count_out[2:0], count_out[3]};
    end
end

endmodule

VT6/tb_ring.v
`include "ring_c.v"

module ring_counter_testbench();
    reg clk, reset;
    wire [3:0] count_out;

    ring_counter dut(clk, reset, count_out);

    initial begin 
        clk = 0;
        forever #5 clk = ~clk;
    end

    initial begin
        $dumpfile("out5.vcd");
        $dumpvars(0, ring_counter_testbench);
        reset = 1;
        #15;
        reset = 0;
        #200;
        $finish;
    end
endmodule

VT6/out5.vcd
$date
	Mon Nov 06 23:12:33 2023
$end
$version
	Icarus Verilog
$end
$timescale
	1s
$end
$scope module ring_counter_testbench $end
$var wire 4 ! count_out [3:0] $end
$var reg 1 " clk $end
$var reg 1 # reset $end
$scope module dut $end
$var wire 1 " clk $end
$var wire 1 # reset $end
$var reg 4 $ count_out [3:0] $end
$upscope $end
$upscope $end
$enddefinitions $end
$comment Show the parameter values. $end
$dumpall
$end
#0
$dumpvars
b1 $
1#
0"
b1 !
$end
#5
1"
#10
0"
#15
b10 !
b10 $
1"
0#
#20
0"
#25
b100 !
b100 $
1"
#30
0"
#35
b1000 !
b1000 $
1"
#40
0"
#45
b1 !
b1 $
1"
#50
0"
#55
b10 !
b10 $
1"
#60
0"
#65
b100 !
b100 $
1"
#70
0"
#75
b1000 !
b1000 $
1"
#80
0"
#85
b1 !
b1 $
1"
#90
0"
#95
b10 !
b10 $
1"
#100
0"
#105
b100 !
b100 $
1"
#110
0"
#115
b1000 !
b1000 $
1"
#120
0"
#125
b1 !
b1 $
1"
#130
0"
#135
b10 !
b10 $
1"
#140
0"
#145
b100 !
b100 $
1"
#150
0"
#155
b1000 !
b1000 $
1"
#160
0"
#165
b1 !
b1 $
1"
#170
0"
#175
b10 !
b10 $
1"
#180
0"
#185
b100 !
b100 $
1"
#190
0"
#195
b1000 !
b1000 $
1"
#200
0"
#205
b1 !
b1 $
1"
#210
0"
#215
b10 !
b10 $
1"
