VT6/rip_2b_counter.v
module ripple_counter (
    input wire clk,
    input wire reset,
    output reg [1:0] count_out
);

always @(posedge clk or posedge reset) begin
    if (reset) begin
        count_out[0] <= 1'b0;
    end else begin
        count_out[0] <= ~count_out[0];
    end
end

always @(negedge count_out[0] or posedge reset) begin
    if (reset) begin
        count_out[1] <= 1'b0;
    end else begin
        count_out[1] <= ~count_out[1];
    end
end

endmodule

VT6/tb_rip_2b.v
`include "rip_2b_counter.v"

module ripple_counter_testbench();
    reg clk, reset;
    wire [1:0] count_out;

    ripple_counter dut(clk, reset, count_out);

    initial begin 
        clk = 0;
        forever #5 clk = ~clk;
    end

    initial begin
        $dumpfile("out6.vcd");
        $dumpvars(0, ripple_counter_testbench);
        reset = 1;
        #15;
        reset = 0;
        #200;
        $finish;
    end
endmodule

VT6/out6.vcd
$date
	Mon Nov 06 23:12:46 2023
$end
$version
	Icarus Verilog
$end
$timescale
	1s
$end
$scope module ripple_counter_testbench $end
$var wire 2 ! count_out [1:0] $end
$var reg 1 " clk $end
$var reg 1 # reset $end
$scope module dut $end
$var wire 1 " clk $end
$var wire 1 # reset $end
$var reg 2 $ count_out [1:0] $end
$upscope $end
$upscope $end
$enddefinitions $end
$comment Show the parameter values. $end
$dumpall
$end
#0
$dumpvars
b0 $
1#
0"
b0 !
$end
#5
1"
#10
0"
#15
b1 !
b1 $
1"
0#
#20
0"
#25
b10 !
b10 $
1"
#30
0"
#35
b11 !
b11 $
1"
#40
0"
#45
b0 !
b0 $
1"
#50
0"
#55
b1 !
b1 $
1"
#60
0"
#65
b10 !
b10 $
1"
#70
0"
#75
b11 !
b11 $
1"
#80
0"
#85
b0 !
b0 $
1"
#90
0"
#95
b1 !
b1 $
1"
#100
0"
#105
b10 !
b10 $
1"
#110
0"
#115
b11 !
b11 $
1"
#120
0"
#125
b0 !
b0 $
1"
#130
0"
#135
b1 !
b1 $
1"
#140
0"
#145
b10 !
b10 $
1"
#150
0"
#155
b11 !
b11 $
1"
#160
0"
#165
b0 !
b0 $
1"
#170
0"
#175
b1 !
b1 $
1"
#180
0"
#185
b10 !
b10 $
1"
#190
0"
#195
b11 !
b11 $
1"
#200
0"
#205
b0 !
b0 $
1"
#210
0"
#215
b1 !
b1 $
1"
