VT_f/univ_register.v
module universal_shift_register (
    input wire clk,
    input wire reset,
    input wire [1:0] mode,
    input wire data_in,
    output reg [3:0] data_out
);

always @(posedge clk or posedge reset) begin
    if (reset) begin
        data_out <= 4'b0000;
    end 
    else begin
        case (mode)
            2'b00: data_out <= {data_out[2:0], data_in}; // Shift left
            2'b01: data_out <= {data_in, data_out[3:1]}; // Shift right
            2'b10: data_out <= data_in; // Parallel load
            default: ; // Hold state
        endcase
    end
end

endmodule

VT_f/tb_univ.v
`include "univ_register.v"

module universal_shift_register_testbench();
    reg clk, reset;
    reg [1:0] mode;
    reg data_in;
    wire [3:0] data_out;

    universal_shift_register dut(clk, reset, mode, data_in, data_out);

    initial begin 
        clk = 0;
        forever #5 clk = ~clk;
    end

    initial begin
        $dumpfile("out1.vcd");
        $dumpvars(0, universal_shift_register_testbench);
        reset = 1;
        #5;
        reset = 0;
        #200;
        $finish;
    end

    initial begin
        mode = 2'b00; // Shift left mode
        data_in=1'b0;
        #10;
        data_in = 1'b1; // Test input
        #10;
        mode = 2'b01; // Shift right mode
        #10;
        data_in = 1'b0; // Test input
        #10;
        mode = 2'b10; // Parallel load mode
        #10;
        data_in = 1'b1; // Test input
        #10;
        mode = 2'b11; // Hold state mode
        #10;
    end
endmodule

VT_f/out1.vcd
$date
	Fri Nov 17 11:42:43 2023
$end
$version
	Icarus Verilog
$end
$timescale
	1s
$end
$scope module universal_shift_register_testbench $end
$var wire 4 ! data_out [3:0] $end
$var reg 1 " clk $end
$var reg 1 # data_in $end
$var reg 2 $ mode [1:0] $end
$var reg 1 % reset $end
$scope module dut $end
$var wire 1 " clk $end
$var wire 1 # data_in $end
$var wire 2 & mode [1:0] $end
$var wire 1 % reset $end
$var reg 4 ' data_out [3:0] $end
$upscope $end
$upscope $end
$enddefinitions $end
#0
$dumpvars
b0 '
b0 &
1%
b0 $
0#
0"
b0 !
$end
#5
0%
1"
#10
0"
1#
#15
b1 !
b1 '
1"
#20
0"
b1 $
b1 &
#25
b1000 !
b1000 '
1"
#30
0"
0#
#35
b100 !
b100 '
1"
#40
0"
b10 $
b10 &
#45
b0 !
b0 '
1"
#50
0"
1#
#55
b1 !
b1 '
1"
#60
0"
b11 $
b11 &
